LICENSE
MANIFEST.in
README.md
requirements.txt
setup.py
pySIR/__init__.py
pySIR/call.py
pySIR/pySIR.py
pySIR/sir_exceptions.py
pySIR.egg-info/PKG-INFO
pySIR.egg-info/SOURCES.txt
pySIR.egg-info/dependency_links.txt
pySIR.egg-info/requires.txt
pySIR.egg-info/top_level.txt