Metadata-Version: 1.1
Name: pySIR
Version: 0.44
Summary: Python API to interact with the SIR agent
Home-page: https://github.com/dbarrosop/pySIR
Author: David Barroso
Author-email: dbarrosop@dravetech.com
License: Apache version 2.0
Platform: UNKNOWN
Classifier: Topic :: System :: Networking
Classifier: License :: OSI Approved :: Apache Software License
Classifier: Programming Language :: Python
Classifier: Programming Language :: Python :: 2
Classifier: Programming Language :: Python :: 2.7
Classifier: Programming Language :: Python :: 3.2
Classifier: Programming Language :: Python :: 3.3
